{
  "lat": -33.87,
  "lon": 18.66,
  "timezone": "Africa/Johannesburg",
  "timezone_offset": 7200,
  "current": {
    "dt": 1606869021,
    "sunrise": 1606879657,
    "sunset": 1606930954,
    "temp": 15.35,
    "feels_like": 9.87,
    "pressure": 1021,
    "humidity": 62,
    "dew_point": 8.12,
    "uvi": 0,
    "clouds": 40,
    "visibility": 10000,
    "wind_speed": 7.2,
    "wind_deg": 160,
    "weather": [
      {
        "id": 802,
        "main": "Clouds",
        "description": "scattered clouds",
        "icon": "03n"
      }
    ]
  },
  "hourly": [
    {
      "dt": 1606867200,
      "temp": 15.35,
      "feels_like": 11.54,
      "pressure": 1021,
      "humidity": 62,
      "dew_point": 8.12,
      "uvi": 0,
      "clouds": 40,
      "visibility": 10000,
      "wind_speed": 4.81,
      "wind_deg": 151,
      "weather": [
        {
          "id": 802,
          "main": "Clouds",
          "description": "scattered clouds",
          "icon": "03n"
        }
      ],
      "pop": 0
    },
    {
      "dt": 1606870800,
      "temp": 13.74,
      "feels_like": 9.95,
      "pressure": 1021,
      "humidity": 68,
      "dew_point": 7.95,
      "uvi": 0,
      "clouds": 20,
      "visibility": 10000,
      "wind_speed": 4.73,
      "wind_deg": 147,
      "weather": [
        {
          "id": 801,
          "main": "Clouds",
          "description": "few clouds",
          "icon": "02n"
        }
      ],
      "pop": 0
    },
    {
      "dt": 1606874400,
      "temp": 12.5,
      "feels_like": 8.88,
      "pressure": 1020,
      "humidity": 72,
      "dew_point": 7.6,
      "uvi": 0,
      "clouds": 9,
      "visibility": 10000,
      "wind_speed": 4.37,
      "wind_deg": 144,
      "weather": [
        {
          "id": 800,
          "main": "Clear",
          "description": "clear sky",
          "icon": "01n"
        }
      ],
      "pop": 0
    },
    {
      "dt": 1606878000,
      "temp": 11.7,
      "feels_like": 8.08,
      "pressure": 1020,
      "humidity": 74,
      "dew_point": 7.23,
      "uvi": 0,
      "clouds": 3,
      "visibility": 10000,
      "wind_speed": 4.25,
      "wind_deg": 147,
      "weather": [
        {
          "id": 800,
          "main": "Clear",
          "description": "clear sky",
          "icon": "01n"
        }
      ],
      "pop": 0
    },
    {
      "dt": 1606881600,
      "temp": 11.71,
      "feels_like": 8.09,
      "pressure": 1020,
      "humidity": 73,
      "dew_point": 7.04,
      "uvi": 0,
      "clouds": 0,
      "visibility": 10000,
      "wind_speed": 4.19,
      "wind_deg": 143,
      "weather": [
        {
          "id": 800,
          "main": "Clear",
          "description": "clear sky",
          "icon": "01d"
        }
      ],
      "pop": 0
    },
    {
      "dt": 1606885200,
      "temp": 13.93,
      "feels_like": 9.9,
      "pressure": 1020,
      "humidity": 62,
      "dew_point": 6.91,
      "uvi": 0.54,
      "clouds": 0,
      "visibility": 10000,
      "wind_speed": 4.68,
      "wind_deg": 138,
      "weather": [
        {
          "id": 800,
          "main": "Clear",
          "description": "clear sky",
          "icon": "01d"
        }
      ],
      "pop": 0
    },
    {
      "dt": 1606888800,
      "temp": 15.84,
      "feels_like": 11.75,
      "pressure": 1021,
      "humidity": 53,
      "dew_point": 6.49,
      "uvi": 1.82,
      "clouds": 0,
      "visibility": 10000,
      "wind_speed": 4.62,
      "wind_deg": 138,
      "weather": [
        {
          "id": 800,
          "main": "Clear",
          "description": "clear sky",
          "icon": "01d"
        }
      ],
      "pop": 0
    },
    {
      "dt": 1606892400,
      "temp": 17.55,
      "feels_like": 13.68,
      "pressure": 1021,
      "humidity": 47,
      "dew_point": 6.14,
      "uvi": 4.05,
      "clouds": 0,
      "visibility": 10000,
      "wind_speed": 4.25,
      "wind_deg": 140,
      "weather": [
        {
          "id": 800,
          "main": "Clear",
          "description": "clear sky",
          "icon": "01d"
        }
      ],
      "pop": 0
    },
    {
      "dt": 1606896000,
      "temp": 19.38,
      "feels_like": 15.34,
      "pressure": 1021,
      "humidity": 41,
      "dew_point": 5.9,
      "uvi": 6.92,
      "clouds": 0,
      "visibility": 10000,
      "wind_speed": 4.39,
      "wind_deg": 148,
      "weather": [
        {
          "id": 800,
          "main": "Clear",
          "description": "clear sky",
          "icon": "01d"
        }
      ],
      "pop": 0
    },
    {
      "dt": 1606899600,
      "temp": 20.98,
      "feels_like": 16.72,
      "pressure": 1020,
      "humidity": 37,
      "dew_point": 5.84,
      "uvi": 9.72,
      "clouds": 0,
      "visibility": 10000,
      "wind_speed": 4.69,
      "wind_deg": 157,
      "weather": [
        {
          "id": 800,
          "main": "Clear",
          "description": "clear sky",
          "icon": "01d"
        }
      ],
      "pop": 0
    },
    {
      "dt": 1606903200,
      "temp": 22.32,
      "feels_like": 17.8,
      "pressure": 1020,
      "humidity": 35,
      "dew_point": 6.14,
      "uvi": 11.71,
      "clouds": 0,
      "visibility": 10000,
      "wind_speed": 5.18,
      "wind_deg": 167,
      "weather": [
        {
          "id": 800,
          "main": "Clear",
          "description": "clear sky",
          "icon": "01d"
        }
      ],
      "pop": 0
    },
    {
      "dt": 1606906800,
      "temp": 23.1,
      "feels_like": 18.07,
      "pressure": 1019,
      "humidity": 34,
      "dew_point": 6.79,
      "uvi": 12.12,
      "clouds": 0,
      "visibility": 10000,
      "wind_speed": 5.99,
      "wind_deg": 175,
      "weather": [
        {
          "id": 800,
          "main": "Clear",
          "description": "clear sky",
          "icon": "01d"
        }
      ],
      "pop": 0
    },
    {
      "dt": 1606910400,
      "temp": 22.91,
      "feels_like": 17.44,
      "pressure": 1018,
      "humidity": 37,
      "dew_point": 7.7,
      "uvi": 10.97,
      "clouds": 0,
      "visibility": 10000,
      "wind_speed": 6.96,
      "wind_deg": 180,
      "weather": [
        {
          "id": 800,
          "main": "Clear",
          "description": "clear sky",
          "icon": "01d"
        }
      ],
      "pop": 0
    },
    {
      "dt": 1606914000,
      "temp": 22.43,
      "feels_like": 16.56,
      "pressure": 1017,
      "humidity": 40,
      "dew_point": 8.28,
      "uvi": 8.63,
      "clouds": 0,
      "visibility": 10000,
      "wind_speed": 7.77,
      "wind_deg": 184,
      "weather": [
        {
          "id": 800,
          "main": "Clear",
          "description": "clear sky",
          "icon": "01d"
        }
      ],
      "pop": 0
    },
    {
      "dt": 1606917600,
      "temp": 21.58,
      "feels_like": 15.37,
      "pressure": 1017,
      "humidity": 43,
      "dew_point": 8.55,
      "uvi": 5.65,
      "clouds": 0,
      "visibility": 10000,
      "wind_speed": 8.37,
      "wind_deg": 185,
      "weather": [
        {
          "id": 800,
          "main": "Clear",
          "description": "clear sky",
          "icon": "01d"
        }
      ],
      "pop": 0
    },
    {
      "dt": 1606921200,
      "temp": 20.71,
      "feels_like": 14.4,
      "pressure": 1017,
      "humidity": 46,
      "dew_point": 8.82,
      "uvi": 2.96,
      "clouds": 0,
      "visibility": 10000,
      "wind_speed": 8.59,
      "wind_deg": 181,
      "weather": [
        {
          "id": 800,
          "main": "Clear",
          "description": "clear sky",
          "icon": "01d"
        }
      ],
      "pop": 0
    },
    {
      "dt": 1606924800,
      "temp": 20.03,
      "feels_like": 14.14,
      "pressure": 1017,
      "humidity": 49,
      "dew_point": 9.07,
      "uvi": 1.13,
      "clouds": 0,
      "visibility": 10000,
      "wind_speed": 8.1,
      "wind_deg": 174,
      "weather": [
        {
          "id": 800,
          "main": "Clear",
          "description": "clear sky",
          "icon": "01d"
        }
      ],
      "pop": 0
    },
    {
      "dt": 1606928400,
      "temp": 18.64,
      "feels_like": 12.53,
      "pressure": 1017,
      "humidity": 53,
      "dew_point": 9.12,
      "uvi": 0.25,
      "clouds": 0,
      "visibility": 10000,
      "wind_speed": 8.37,
      "wind_deg": 170,
      "weather": [
        {
          "id": 800,
          "main": "Clear",
          "description": "clear sky",
          "icon": "01d"
        }
      ],
      "pop": 0
    },
    {
      "dt": 1606932000,
      "temp": 16.75,
      "feels_like": 11.51,
      "pressure": 1017,
      "humidity": 59,
      "dew_point": 8.77,
      "uvi": 0,
      "clouds": 0,
      "visibility": 10000,
      "wind_speed": 7.07,
      "wind_deg": 164,
      "weather": [
        {
          "id": 800,
          "main": "Clear",
          "description": "clear sky",
          "icon": "01n"
        }
      ],
      "pop": 0
    },
    {
      "dt": 1606935600,
      "temp": 15.66,
      "feels_like": 10.98,
      "pressure": 1018,
      "humidity": 63,
      "dew_point": 8.74,
      "uvi": 0,
      "clouds": 0,
      "visibility": 10000,
      "wind_speed": 6.25,
      "wind_deg": 162,
      "weather": [
        {
          "id": 800,
          "main": "Clear",
          "description": "clear sky",
          "icon": "01n"
        }
      ],
      "pop": 0
    },
    {
      "dt": 1606939200,
      "temp": 14.95,
      "feels_like": 10.71,
      "pressure": 1019,
      "humidity": 65,
      "dew_point": 8.5,
      "uvi": 0,
      "clouds": 0,
      "visibility": 10000,
      "wind_speed": 5.54,
      "wind_deg": 157,
      "weather": [
        {
          "id": 800,
          "main": "Clear",
          "description": "clear sky",
          "icon": "01n"
        }
      ],
      "pop": 0
    },
    {
      "dt": 1606942800,
      "temp": 14.19,
      "feels_like": 10.14,
      "pressure": 1019,
      "humidity": 67,
      "dew_point": 8.26,
      "uvi": 0,
      "clouds": 0,
      "visibility": 10000,
      "wind_speed": 5.17,
      "wind_deg": 152,
      "weather": [
        {
          "id": 800,
          "main": "Clear",
          "description": "clear sky",
          "icon": "01n"
        }
      ],
      "pop": 0
    },
    {
      "dt": 1606946400,
      "temp": 13.39,
      "feels_like": 9.57,
      "pressure": 1018,
      "humidity": 70,
      "dew_point": 8.23,
      "uvi": 0,
      "clouds": 0,
      "visibility": 10000,
      "wind_speed": 4.8,
      "wind_deg": 150,
      "weather": [
        {
          "id": 800,
          "main": "Clear",
          "description": "clear sky",
          "icon": "01n"
        }
      ],
      "pop": 0
    },
    {
      "dt": 1606950000,
      "temp": 12.59,
      "feels_like": 9.09,
      "pressure": 1018,
      "humidity": 74,
      "dew_point": 8.26,
      "uvi": 0,
      "clouds": 0,
      "visibility": 10000,
      "wind_speed": 4.36,
      "wind_deg": 148,
      "weather": [
        {
          "id": 800,
          "main": "Clear",
          "description": "clear sky",
          "icon": "01n"
        }
      ],
      "pop": 0
    },
    {
      "dt": 1606953600,
      "temp": 12.17,
      "feels_like": 8.77,
      "pressure": 1017,
      "humidity": 76,
      "dew_point": 8.25,
      "uvi": 0,
      "clouds": 0,
      "visibility": 10000,
      "wind_speed": 4.21,
      "wind_deg": 148,
      "weather": [
        {
          "id": 800,
          "main": "Clear",
          "description": "clear sky",
          "icon": "01n"
        }
      ],
      "pop": 0
    },
    {
      "dt": 1606957200,
      "temp": 11.86,
      "feels_like": 8.54,
      "pressure": 1017,
      "humidity": 78,
      "dew_point": 8.21,
      "uvi": 0,
      "clouds": 0,
      "visibility": 10000,
      "wind_speed": 4.13,
      "wind_deg": 152,
      "weather": [
        {
          "id": 800,
          "main": "Clear",
          "description": "clear sky",
          "icon": "01n"
        }
      ],
      "pop": 0
    },
    {
      "dt": 1606960800,
      "temp": 11.53,
      "feels_like": 8.32,
      "pressure": 1017,
      "humidity": 78,
      "dew_point": 7.98,
      "uvi": 0,
      "clouds": 0,
      "visibility": 10000,
      "wind_speed": 3.86,
      "wind_deg": 146,
      "weather": [
        {
          "id": 800,
          "main": "Clear",
          "description": "clear sky",
          "icon": "01n"
        }
      ],
      "pop": 0
    },
    {
      "dt": 1606964400,
      "temp": 11.36,
      "feels_like": 8.11,
      "pressure": 1017,
      "humidity": 78,
      "dew_point": 7.69,
      "uvi": 0,
      "clouds": 0,
      "visibility": 10000,
      "wind_speed": 3.87,
      "wind_deg": 147,
      "weather": [
        {
          "id": 800,
          "main": "Clear",
          "description": "clear sky",
          "icon": "01n"
        }
      ],
      "pop": 0
    },
    {
      "dt": 1606968000,
      "temp": 11.73,
      "feels_like": 8.51,
      "pressure": 1017,
      "humidity": 76,
      "dew_point": 7.67,
      "uvi": 0,
      "clouds": 0,
      "visibility": 10000,
      "wind_speed": 3.81,
      "wind_deg": 146,
      "weather": [
        {
          "id": 800,
          "main": "Clear",
          "description": "clear sky",
          "icon": "01d"
        }
      ],
      "pop": 0
    },
    {
      "dt": 1606971600,
      "temp": 14.31,
      "feels_like": 11.12,
      "pressure": 1017,
      "humidity": 64,
      "dew_point": 7.67,
      "uvi": 0.55,
      "clouds": 0,
      "visibility": 10000,
      "wind_speed": 3.76,
      "wind_deg": 145,
      "weather": [
        {
          "id": 800,
          "main": "Clear",
          "description": "clear sky",
          "icon": "01d"
        }
      ],
      "pop": 0
    },
    {
      "dt": 1606975200,
      "temp": 17.12,
      "feels_like": 13.75,
      "pressure": 1018,
      "humidity": 52,
      "dew_point": 7.24,
      "uvi": 1.84,
      "clouds": 0,
      "visibility": 10000,
      "wind_speed": 3.88,
      "wind_deg": 153,
      "weather": [
        {
          "id": 800,
          "main": "Clear",
          "description": "clear sky",
          "icon": "01d"
        }
      ],
      "pop": 0
    },
    {
      "dt": 1606978800,
      "temp": 19.77,
      "feels_like": 15.92,
      "pressure": 1018,
      "humidity": 42,
      "dew_point": 6.67,
      "uvi": 4,
      "clouds": 0,
      "visibility": 10000,
      "wind_speed": 4.34,
      "wind_deg": 160,
      "weather": [
        {
          "id": 800,
          "main": "Clear",
          "description": "clear sky",
          "icon": "01d"
        }
      ],
      "pop": 0
    },
    {
      "dt": 1606982400,
      "temp": 21.96,
      "feels_like": 17.46,
      "pressure": 1018,
      "humidity": 35,
      "dew_point": 5.95,
      "uvi": 6.84,
      "clouds": 45,
      "visibility": 10000,
      "wind_speed": 5.06,
      "wind_deg": 170,
      "weather": [
        {
          "id": 802,
          "main": "Clouds",
          "description": "scattered clouds",
          "icon": "03d"
        }
      ],
      "pop": 0
    },
    {
      "dt": 1606986000,
      "temp": 23.73,
      "feels_like": 18.57,
      "pressure": 1018,
      "humidity": 30,
      "dew_point": 5.53,
      "uvi": 9.58,
      "clouds": 60,
      "visibility": 10000,
      "wind_speed": 5.8,
      "wind_deg": 173,
      "weather": [
        {
          "id": 803,
          "main": "Clouds",
          "description": "broken clouds",
          "icon": "04d"
        }
      ],
      "pop": 0
    },
    {
      "dt": 1606989600,
      "temp": 24.68,
      "feels_like": 18.9,
      "pressure": 1017,
      "humidity": 29,
      "dew_point": 5.89,
      "uvi": 11.54,
      "clouds": 55,
      "visibility": 10000,
      "wind_speed": 6.78,
      "wind_deg": 174,
      "weather": [
        {
          "id": 803,
          "main": "Clouds",
          "description": "broken clouds",
          "icon": "04d"
        }
      ],
      "pop": 0
    },
    {
      "dt": 1606993200,
      "temp": 25.24,
      "feels_like": 19.11,
      "pressure": 1016,
      "humidity": 30,
      "dew_point": 6.49,
      "uvi": 11.95,
      "clouds": 44,
      "visibility": 10000,
      "wind_speed": 7.57,
      "wind_deg": 175,
      "weather": [
        {
          "id": 802,
          "main": "Clouds",
          "description": "scattered clouds",
          "icon": "03d"
        }
      ],
      "pop": 0
    },
    {
      "dt": 1606996800,
      "temp": 24.82,
      "feels_like": 18.11,
      "pressure": 1016,
      "humidity": 33,
      "dew_point": 7.72,
      "uvi": 10.81,
      "clouds": 37,
      "visibility": 10000,
      "wind_speed": 8.73,
      "wind_deg": 178,
      "weather": [
        {
          "id": 802,
          "main": "Clouds",
          "description": "scattered clouds",
          "icon": "03d"
        }
      ],
      "pop": 0
    },
    {
      "dt": 1607000400,
      "temp": 23.58,
      "feels_like": 16.33,
      "pressure": 1016,
      "humidity": 39,
      "dew_point": 9.18,
      "uvi": 8.68,
      "clouds": 0,
      "visibility": 10000,
      "wind_speed": 9.97,
      "wind_deg": 181,
      "weather": [
        {
          "id": 800,
          "main": "Clear",
          "description": "clear sky",
          "icon": "01d"
        }
      ],
      "pop": 0
    },
    {
      "dt": 1607004000,
      "temp": 22.67,
      "feels_like": 15.52,
      "pressure": 1016,
      "humidity": 44,
      "dew_point": 9.91,
      "uvi": 5.68,
      "clouds": 0,
      "visibility": 10000,
      "wind_speed": 10.19,
      "wind_deg": 178,
      "weather": [
        {
          "id": 800,
          "main": "Clear",
          "description": "clear sky",
          "icon": "01d"
        }
      ],
      "pop": 0
    },
    {
      "dt": 1607007600,
      "temp": 21.54,
      "feels_like": 14.59,
      "pressure": 1016,
      "humidity": 49,
      "dew_point": 10.53,
      "uvi": 2.98,
      "clouds": 0,
      "visibility": 10000,
      "wind_speed": 10.13,
      "wind_deg": 175,
      "weather": [
        {
          "id": 800,
          "main": "Clear",
          "description": "clear sky",
          "icon": "01d"
        }
      ],
      "pop": 0
    },
    {
      "dt": 1607011200,
      "temp": 20.47,
      "feels_like": 13.95,
      "pressure": 1016,
      "humidity": 55,
      "dew_point": 11.17,
      "uvi": 1.13,
      "clouds": 0,
      "visibility": 10000,
      "wind_speed": 9.82,
      "wind_deg": 172,
      "weather": [
        {
          "id": 800,
          "main": "Clear",
          "description": "clear sky",
          "icon": "01d"
        }
      ],
      "pop": 0
    },
    {
      "dt": 1607014800,
      "temp": 19.05,
      "feels_like": 13.33,
      "pressure": 1017,
      "humidity": 61,
      "dew_point": 11.39,
      "uvi": 0.25,
      "clouds": 0,
      "visibility": 10000,
      "wind_speed": 8.78,
      "wind_deg": 167,
      "weather": [
        {
          "id": 800,
          "main": "Clear",
          "description": "clear sky",
          "icon": "01d"
        }
      ],
      "pop": 0
    },
    {
      "dt": 1607018400,
      "temp": 17.37,
      "feels_like": 12.38,
      "pressure": 1017,
      "humidity": 67,
      "dew_point": 11.36,
      "uvi": 0,
      "clouds": 0,
      "visibility": 10000,
      "wind_speed": 7.67,
      "wind_deg": 163,
      "weather": [
        {
          "id": 800,
          "main": "Clear",
          "description": "clear sky",
          "icon": "01n"
        }
      ],
      "pop": 0
    },
    {
      "dt": 1607022000,
      "temp": 16.48,
      "feels_like": 11.94,
      "pressure": 1018,
      "humidity": 71,
      "dew_point": 11.3,
      "uvi": 0,
      "clouds": 0,
      "visibility": 10000,
      "wind_speed": 7.03,
      "wind_deg": 160,
      "weather": [
        {
          "id": 800,
          "main": "Clear",
          "description": "clear sky",
          "icon": "01n"
        }
      ],
      "pop": 0
    },
    {
      "dt": 1607025600,
      "temp": 15.88,
      "feels_like": 11.89,
      "pressure": 1019,
      "humidity": 74,
      "dew_point": 11.41,
      "uvi": 0,
      "clouds": 0,
      "visibility": 10000,
      "wind_speed": 6.26,
      "wind_deg": 157,
      "weather": [
        {
          "id": 800,
          "main": "Clear",
          "description": "clear sky",
          "icon": "01n"
        }
      ],
      "pop": 0
    },
    {
      "dt": 1607029200,
      "temp": 15.44,
      "feels_like": 11.71,
      "pressure": 1019,
      "humidity": 76,
      "dew_point": 11.39,
      "uvi": 0,
      "clouds": 0,
      "visibility": 10000,
      "wind_speed": 5.89,
      "wind_deg": 153,
      "weather": [
        {
          "id": 800,
          "main": "Clear",
          "description": "clear sky",
          "icon": "01n"
        }
      ],
      "pop": 0
    },
    {
      "dt": 1607032800,
      "temp": 15.02,
      "feels_like": 11.35,
      "pressure": 1019,
      "humidity": 76,
      "dew_point": 11,
      "uvi": 0,
      "clouds": 0,
      "visibility": 10000,
      "wind_speed": 5.63,
      "wind_deg": 151,
      "weather": [
        {
          "id": 800,
          "main": "Clear",
          "description": "clear sky",
          "icon": "01n"
        }
      ],
      "pop": 0
    },
    {
      "dt": 1607036400,
      "temp": 14.68,
      "feels_like": 10.98,
      "pressure": 1018,
      "humidity": 75,
      "dew_point": 10.4,
      "uvi": 0,
      "clouds": 0,
      "visibility": 10000,
      "wind_speed": 5.46,
      "wind_deg": 152,
      "weather": [
        {
          "id": 800,
          "main": "Clear",
          "description": "clear sky",
          "icon": "01n"
        }
      ],
      "pop": 0
    }
  ],
  "daily": [
    {
      "dt": 1606903200,
      "sunrise": 1606879657,
      "sunset": 1606930954,
      "temp": {
        "day": 22.32,
        "min": 11.7,
        "max": 23.1,
        "night": 14.19,
        "eve": 20.03,
        "morn": 11.71
      },
      "feels_like": {
        "day": 17.8,
        "night": 10.14,
        "eve": 14.14,
        "morn": 8.09
      },
      "pressure": 1020,
      "humidity": 35,
      "dew_point": 6.14,
      "wind_speed": 5.18,
      "wind_deg": 167,
      "weather": [
        {
          "id": 800,
          "main": "Clear",
          "description": "clear sky",
          "icon": "01d"
        }
      ],
      "clouds": 0,
      "pop": 0,
      "uvi": 12.12
    },
    {
      "dt": 1606989600,
      "sunrise": 1606966052,
      "sunset": 1607017405,
      "temp": {
        "day": 24.68,
        "min": 11.36,
        "max": 25.24,
        "night": 15.44,
        "eve": 20.47,
        "morn": 11.73
      },
      "feels_like": {
        "day": 18.9,
        "night": 11.71,
        "eve": 13.95,
        "morn": 8.51
      },
      "pressure": 1017,
      "humidity": 29,
      "dew_point": 5.89,
      "wind_speed": 6.78,
      "wind_deg": 174,
      "weather": [
        {
          "id": 803,
          "main": "Clouds",
          "description": "broken clouds",
          "icon": "04d"
        }
      ],
      "clouds": 55,
      "pop": 0,
      "uvi": 11.95
    },
    {
      "dt": 1607076000,
      "sunrise": 1607052449,
      "sunset": 1607103856,
      "temp": {
        "day": 24.6,
        "min": 13.91,
        "max": 26.22,
        "night": 15.7,
        "eve": 22.36,
        "morn": 14.06
      },
      "feels_like": {
        "day": 21.62,
        "night": 12.29,
        "eve": 17.52,
        "morn": 10.89
      },
      "pressure": 1019,
      "humidity": 38,
      "dew_point": 9.53,
      "wind_speed": 4.07,
      "wind_deg": 138,
      "weather": [
        {
          "id": 800,
          "main": "Clear",
          "description": "clear sky",
          "icon": "01d"
        }
      ],
      "clouds": 0,
      "pop": 0,
      "uvi": 12.64
    },
    {
      "dt": 1607162400,
      "sunrise": 1607138848,
      "sunset": 1607190306,
      "temp": {
        "day": 24.68,
        "min": 13.57,
        "max": 28.28,
        "night": 17.05,
        "eve": 26,
        "morn": 13.57
      },
      "feels_like": {
        "day": 22.22,
        "night": 14.64,
        "eve": 21.53,
        "morn": 11.27
      },
      "pressure": 1014,
      "humidity": 41,
      "dew_point": 10.57,
      "wind_speed": 3.79,
      "wind_deg": 135,
      "weather": [
        {
          "id": 800,
          "main": "Clear",
          "description": "clear sky",
          "icon": "01d"
        }
      ],
      "clouds": 10,
      "pop": 0,
      "uvi": 12.94
    },
    {
      "dt": 1607248800,
      "sunrise": 1607225249,
      "sunset": 1607276755,
      "temp": {
        "day": 23.34,
        "min": 14.47,
        "max": 23.59,
        "night": 16.55,
        "eve": 22.14,
        "morn": 14.47
      },
      "feels_like": {
        "day": 19.84,
        "night": 11.72,
        "eve": 16.75,
        "morn": 13.25
      },
      "pressure": 1013,
      "humidity": 51,
      "dew_point": 12.75,
      "wind_speed": 6.16,
      "wind_deg": 167,
      "weather": [
        {
          "id": 801,
          "main": "Clouds",
          "description": "few clouds",
          "icon": "02d"
        }
      ],
      "clouds": 12,
      "pop": 0.1,
      "uvi": 12.38
    },
    {
      "dt": 1607335200,
      "sunrise": 1607311651,
      "sunset": 1607363202,
      "temp": {
        "day": 24.49,
        "min": 14.75,
        "max": 27.53,
        "night": 17.14,
        "eve": 26.24,
        "morn": 14.75
      },
      "feels_like": {
        "day": 20.88,
        "night": 15.82,
        "eve": 21.83,
        "morn": 12.02
      },
      "pressure": 1016,
      "humidity": 46,
      "dew_point": 12.13,
      "wind_speed": 6.09,
      "wind_deg": 129,
      "weather": [
        {
          "id": 800,
          "main": "Clear",
          "description": "clear sky",
          "icon": "01d"
        }
      ],
      "clouds": 4,
      "pop": 0.05,
      "uvi": 13
    },
    {
      "dt": 1607421600,
      "sunrise": 1607398056,
      "sunset": 1607449649,
      "temp": {
        "day": 26.69,
        "min": 14.1,
        "max": 28.16,
        "night": 19.05,
        "eve": 26.1,
        "morn": 14.1
      },
      "feels_like": {
        "day": 25.93,
        "night": 19.25,
        "eve": 23.6,
        "morn": 13.21
      },
      "pressure": 1015,
      "humidity": 33,
      "dew_point": 9.44,
      "wind_speed": 0.8,
      "wind_deg": 104,
      "weather": [
        {
          "id": 803,
          "main": "Clouds",
          "description": "broken clouds",
          "icon": "04d"
        }
      ],
      "clouds": 82,
      "pop": 0,
      "uvi": 13
    },
    {
      "dt": 1607508000,
      "sunrise": 1607484462,
      "sunset": 1607536095,
      "temp": {
        "day": 24.57,
        "min": 17.59,
        "max": 24.57,
        "night": 18.07,
        "eve": 22.16,
        "morn": 17.59
      },
      "feels_like": {
        "day": 21.09,
        "night": 16.64,
        "eve": 20.03,
        "morn": 16.72
      },
      "pressure": 1011,
      "humidity": 48,
      "dew_point": 13.16,
      "wind_speed": 6.22,
      "wind_deg": 321,
      "weather": [
        {
          "id": 804,
          "main": "Clouds",
          "description": "overcast clouds",
          "icon": "04d"
        }
      ],
      "clouds": 100,
      "pop": 0,
      "uvi": 13
    }
  ]
}
